rename_movie.py
rename_movie-1.2.1.dist-info/entry_points.txt
rename_movie-1.2.1.dist-info/WHEEL
rename_movie-1.2.1.dist-info/METADATA
rename_movie-1.2.1.dist-info/RECORD
