Metadata-Version: 2.1
Name: rename-movie
Version: 1.2.1
Summary: Rename and organize movies
License: MIT
Author: Dima Koskin
Author-email: dmksknn@gmail.com
Requires-Python: >=3.8,<4.0
Classifier: License :: OSI Approved :: MIT License
Classifier: Programming Language :: Python :: 3
Classifier: Programming Language :: Python :: 3.8
Requires-Dist: isle (>=0.6.0,<0.7.0)
Requires-Dist: macos-tags (>=1.5.1,<2.0.0)
